Metadata-Version: 2.1
Name: changelogmd
Version: 0.2.0
Summary: Python module and CLI tool for CHANGELOG.md manipulation.
Home-page: https://github.com/gronke/py-changelogmd
Author: Stefan Grönke
Author-email: stefan@gronke.net
License: UNKNOWN
Platform: UNKNOWN
Requires-Python: >=3.6
